<?xml version="1.0" encoding="UTF-8"?><?xml-stylesheet type='text/xsl' href='_UpgradeReport_Files/UpgradeReport.xslt'?><UpgradeLog>
<Properties><Property Name="Solution" Value="CsharpNote">
</Property><Property Name="Solution File" Value="D:\Work\DotNet3\Csharp3\CsharpNote\CsharpNote.sln">
</Property><Property Name="Date" Value="2009年1月28日">
</Property><Property Name="Time" Value="下午 13:58:29">
</Property></Properties><Event ErrorLevel="0" Project="BasicDelegateDemo" Source="BasicDelegateDemo\BasicDelegateDemo.csproj" Description="Project file successfully backed up as D:\Work\DotNet3\Csharp3\CsharpNote\Backup\BasicDelegateDemo.csproj">
</Event><Event ErrorLevel="0" Project="BasicDelegateDemo" Source="BasicDelegateDemo\Program.cs" Description="File successfully backed up as D:\Work\DotNet3\Csharp3\CsharpNote\Backup\Program.cs">
</Event><Event ErrorLevel="0" Project="BasicDelegateDemo" Source="BasicDelegateDemo\Properties\AssemblyInfo.cs" Description="File successfully backed up as D:\Work\DotNet3\Csharp3\CsharpNote\Backup\Properties\AssemblyInfo.cs">
</Event><Event ErrorLevel="0" Project="BasicDelegateDemo" Source="BasicDelegateDemo\BasicDelegateDemo.csproj" Description="Project converted successfully">
</Event><Event ErrorLevel="3" Project="BasicDelegateDemo" Source="BasicDelegateDemo\BasicDelegateDemo.csproj" Description="Converted">
</Event><Event ErrorLevel="0" Project="BasicDelegateDemo" Source="BasicDelegateDemo\BasicDelegateDemo.csproj" Description="Scan complete: Upgrade not required for project files.">
</Event></UpgradeLog>